[
  {
    "id": 1,
    "name": "FROST CUP 16OZ",
    "slug": "frost-cup-16oz",
    "category_id": 1,
    "best_for": "Milk Tea, Cold Brew, Boba",
    "description": "High-clarity PET cup with premium cold-ink flexo printing. 16oz standard mouth.",
    "base_price": 3.50,
    "min_order": 500,
    "stock": 12000,
    "stock_threshold": 1000,
    "main_image": null,
    "images": [],
    "tags": ["cup", "pet", "16oz", "milk-tea"],
    "rating": 4.8,
    "rating_count": 142,
    "is_active": true,
    "screenplate_ids": [1, 2]
  },
  {
    "id": 2,
    "name": "FROST CUP 22OZ",
    "slug": "frost-cup-22oz",
    "category_id": 1,
    "best_for": "Large Format, Frappe, Smoothie",
    "description": "Extended capacity PET cup. Wide mouth compatible with dome lids.",
    "base_price": 4.20,
    "min_order": 500,
    "stock": 8500,
    "stock_threshold": 1000,
    "main_image": null,
    "images": [],
    "tags": ["cup", "pet", "22oz"],
    "rating": 4.6,
    "rating_count": 89,
    "is_active": true,
    "screenplate_ids": [1, 3]
  },
  {
    "id": 3,
    "name": "PP HOT CUP 8OZ",
    "slug": "pp-hot-cup-8oz",
    "category_id": 1,
    "best_for": "Coffee, Hot Tea, Espresso",
    "description": "Heat-resistant polypropylene cup. 8oz with single-color or CMYK print.",
    "base_price": 3.80,
    "min_order": 500,
    "stock": 750,
    "stock_threshold": 1000,
    "main_image": null,
    "images": [],
    "tags": ["cup", "pp", "hot", "8oz"],
    "rating": 4.5,
    "rating_count": 67,
    "is_active": true,
    "screenplate_ids": [2]
  },
  {
    "id": 4,
    "name": "KRAFT BAG SM",
    "slug": "kraft-bag-sm",
    "category_id": 2,
    "best_for": "Pastry, Café Retail, Takeaway",
    "description": "Small kraft paper bag. 1-color flexo print. 100% recyclable stock.",
    "base_price": 5.50,
    "min_order": 300,
    "stock": 6200,
    "stock_threshold": 500,
    "main_image": null,
    "images": [],
    "tags": ["bag", "kraft", "small", "eco"],
    "rating": 4.7,
    "rating_count": 215,
    "is_active": true,
    "screenplate_ids": [4]
  },
  {
    "id": 5,
    "name": "KRAFT BAG LG",
    "slug": "kraft-bag-lg",
    "category_id": 2,
    "best_for": "Group Orders, Gift Sets, Retail",
    "description": "Large kraft bag with full-bleed CMYK print. Reinforced handles.",
    "base_price": 7.80,
    "min_order": 200,
    "stock": 3100,
    "stock_threshold": 500,
    "main_image": null,
    "images": [],
    "tags": ["bag", "kraft", "large"],
    "rating": 4.9,
    "rating_count": 178,
    "is_active": true,
    "screenplate_ids": [4, 5]
  },
  {
    "id": 6,
    "name": "VINYL LABEL 60MM",
    "slug": "vinyl-label-60mm",
    "category_id": 3,
    "best_for": "Cup Branding, Bottle Label, Product ID",
    "description": "Waterproof vinyl label. 60mm circle. CMYK + gloss laminate.",
    "base_price": 0.85,
    "min_order": 1000,
    "stock": 45000,
    "stock_threshold": 5000,
    "main_image": null,
    "images": [],
    "tags": ["label", "vinyl", "60mm", "waterproof"],
    "rating": 4.8,
    "rating_count": 334,
    "is_active": true,
    "screenplate_ids": [6]
  },
  {
    "id": 7,
    "name": "MATTE LABEL RECT",
    "slug": "matte-label-rect",
    "category_id": 3,
    "best_for": "Packaging, Jar Labels, Premium Retail",
    "description": "Matte paper label. 90x50mm rectangle. Spot UV optional.",
    "base_price": 0.90,
    "min_order": 1000,
    "stock": 28000,
    "stock_threshold": 5000,
    "main_image": null,
    "images": [],
    "tags": ["label", "matte", "rectangle"],
    "rating": 4.6,
    "rating_count": 201,
    "is_active": true,
    "screenplate_ids": [6, 7]
  },
  {
    "id": 8,
    "name": "SEALING FILM ROLL",
    "slug": "sealing-film-roll",
    "category_id": 4,
    "best_for": "Boba, Milk Tea, Juice Seal",
    "description": "Cup sealing film. 3200 seals per roll. Custom print available.",
    "base_price": 850.00,
    "min_order": 1,
    "stock": 85,
    "stock_threshold": 20,
    "main_image": null,
    "images": [],
    "tags": ["sealing", "film", "roll"],
    "rating": 4.7,
    "rating_count": 93,
    "is_active": true,
    "screenplate_ids": [8]
  },
  {
    "id": 9,
    "name": "DOME LID 90MM",
    "slug": "dome-lid-90mm",
    "category_id": 1,
    "best_for": "Boba, Layered Drinks, Cream Top",
    "description": "90mm dome lid. Compatible with Frost Cup 16oz/22oz. Can carry logo emboss.",
    "base_price": 1.20,
    "min_order": 1000,
    "stock": 320,
    "stock_threshold": 500,
    "main_image": null,
    "images": [],
    "tags": ["lid", "dome", "90mm"],
    "rating": 4.4,
    "rating_count": 56,
    "is_active": true,
    "screenplate_ids": [1]
  },
  {
    "id": 10,
    "name": "FLAT LID 90MM",
    "slug": "flat-lid-90mm",
    "category_id": 1,
    "best_for": "Hot Drinks, Takeout Coffee",
    "description": "Flat sip-through lid. 90mm diameter. PS material.",
    "base_price": 1.00,
    "min_order": 1000,
    "stock": 15000,
    "stock_threshold": 1000,
    "main_image": null,
    "images": [],
    "tags": ["lid", "flat", "90mm", "hot"],
    "rating": 4.3,
    "rating_count": 44,
    "is_active": true,
    "screenplate_ids": []
  },
  {
    "id": 11,
    "name": "KRAFT BAG MD",
    "slug": "kraft-bag-md",
    "category_id": 2,
    "best_for": "2-Cup Carrier, Snack Pack",
    "description": "Medium kraft bag. Gusseted bottom. Spot color print.",
    "base_price": 6.50,
    "min_order": 200,
    "stock": 4800,
    "stock_threshold": 500,
    "main_image": null,
    "images": [],
    "tags": ["bag", "kraft", "medium"],
    "rating": 4.5,
    "rating_count": 132,
    "is_active": true,
    "screenplate_ids": [4]
  },
  {
    "id": 12,
    "name": "CLEAR STICKER 50MM",
    "slug": "clear-sticker-50mm",
    "category_id": 3,
    "best_for": "See-Through Brand Mark, Premium Packaging",
    "description": "Transparent vinyl sticker. 50mm circle. CMYK white ink base.",
    "base_price": 0.95,
    "min_order": 500,
    "stock": 22000,
    "stock_threshold": 2000,
    "main_image": null,
    "images": [],
    "tags": ["sticker", "clear", "vinyl", "50mm"],
    "rating": 4.7,
    "rating_count": 167,
    "is_active": true,
    "screenplate_ids": [6]
  }
]
